{
  "scriptId": "308",
  "url": "file:///Users/gruposeb/www/ten.net/src/storage/schema.ts",
  "functions": [
    {
      "functionName": "",
      "ranges": [
        {
          "startOffset": 0,
          "endOffset": 3778,
          "count": 1
        }
      ],
      "isBlockCoverage": true
    },
    {
      "functionName": "migrate",
      "ranges": [
        {
          "startOffset": 630,
          "endOffset": 781,
          "count": 3
        }
      ],
      "isBlockCoverage": true
    },
    {
      "functionName": "migrate",
      "ranges": [
        {
          "startOffset": 944,
          "endOffset": 2115,
          "count": 3
        },
        {
          "startOffset": 1114,
          "endOffset": 2109,
          "count": 0
        }
      ],
      "isBlockCoverage": true
    },
    {
      "functionName": "migrate",
      "ranges": [
        {
          "startOffset": 2249,
          "endOffset": 2755,
          "count": 3
        },
        {
          "startOffset": 2419,
          "endOffset": 2749,
          "count": 0
        }
      ],
      "isBlockCoverage": true
    },
    {
      "functionName": "getSchemaVersion",
      "ranges": [
        {
          "startOffset": 2839,
          "endOffset": 2955,
          "count": 8
        },
        {
          "startOffset": 2948,
          "endOffset": 2952,
          "count": 4
        }
      ],
      "isBlockCoverage": true
    },
    {
      "functionName": "setSchemaVersion",
      "ranges": [
        {
          "startOffset": 2993,
          "endOffset": 3086,
          "count": 9
        }
      ],
      "isBlockCoverage": true
    },
    {
      "functionName": "runMigrations",
      "ranges": [
        {
          "startOffset": 3333,
          "endOffset": 3777,
          "count": 5
        },
        {
          "startOffset": 3469,
          "endOffset": 3501,
          "count": 2
        },
        {
          "startOffset": 3501,
          "endOffset": 3653,
          "count": 3
        },
        {
          "startOffset": 3653,
          "endOffset": 3742,
          "count": 9
        },
        {
          "startOffset": 3742,
          "endOffset": 3776,
          "count": 3
        }
      ],
      "isBlockCoverage": true
    },
    {
      "functionName": "",
      "ranges": [
        {
          "startOffset": 3538,
          "endOffset": 3569,
          "count": 9
        }
      ],
      "isBlockCoverage": true
    },
    {
      "functionName": "",
      "ranges": [
        {
          "startOffset": 3587,
          "endOffset": 3616,
          "count": 6
        }
      ],
      "isBlockCoverage": true
    }
  ]
}
